{
  "etf": "XLB",
  "schema_id": "default",
  "as_of": "2026-07-11",
  "_meta": {
    "holdings_count": 10,
    "weight_coverage_pct": 58.31,
    "outliers_dropped": {
      "trailingPE": 1
    },
    "skipped_holdings": [],
    "schema_dispatch": {
      "default": 10
    },
    "source": "yfinance funds_data + data-markets memo-fetch"
  },
  "multiples": {
    "trailingPE": 31.31785648328478,
    "forwardPE": null,
    "evEbitda": 26.684951022275644,
    "priceToSales": 4.876034251405075,
    "priceToBook": 5.841773696362274
  },
  "indicators": {
    "gross_margin": 33.7907063375968,
    "operating_margin": 19.056123403678992,
    "FCF_yield": 2.388758701552355
  }
}
