{
  "etf": "XLF",
  "schema_id": "bank",
  "as_of": "2026-05-30",
  "_meta": {
    "holdings_count": 10,
    "weight_coverage_pct": 56.23,
    "outliers_dropped": {},
    "skipped_holdings": [],
    "schema_dispatch": {
      "default": 4,
      "bank": 4,
      "asset-manager": 2
    },
    "source": "yfinance funds_data + data-us memo-fetch"
  },
  "multiples": {
    "trailingPE": 16.838624614570705,
    "forwardPE": null,
    "priceToBook": 9.247879892802569,
    "priceToTangibleBook": 2.0265924445883385
  },
  "indicators": {
    "ROE": 13.114423232836902
  }
}
